edgegap_scheduling/__init__.py
edgegap_scheduling/_depends.py
edgegap_scheduling/_model.py
edgegap_scheduling/_runner.py
edgegap_scheduling/_scheduler.py
edgegap_scheduling/_signature.py
edgegap_scheduling/_singleton.py
edgegap_scheduling/_sleep.py
edgegap_scheduling/_state.py
edgegap_scheduling/_task.py
edgegap_scheduling/errors/__init__.py
edgegap_scheduling/errors/_errors.py
edgegap_scheduling-1.11.12.dist-info/LICENSE
edgegap_scheduling-1.11.12.dist-info/METADATA
edgegap_scheduling-1.11.12.dist-info/WHEEL
edgegap_scheduling-1.11.12.dist-info/RECORD
